CHANGES.txt
MANIFEST.in
README.rst
buildout.cfg
minitage.cfg
setup.cfg
setup.py
src/minitage/__init__.py
src/minitage.recipe.egg.egg-info/PKG-INFO
src/minitage.recipe.egg.egg-info/SOURCES.txt
src/minitage.recipe.egg.egg-info/dependency_links.txt
src/minitage.recipe.egg.egg-info/entry_points.txt
src/minitage.recipe.egg.egg-info/namespace_packages.txt
src/minitage.recipe.egg.egg-info/not-zip-safe
src/minitage.recipe.egg.egg-info/requires.txt
src/minitage.recipe.egg.egg-info/top_level.txt
src/minitage/recipe/__init__.py
src/minitage/recipe/egg/README.txt
src/minitage/recipe/egg/__init__.py
src/minitage/recipe/egg/egg.py
src/minitage/recipe/egg/testing.py
src/minitage/recipe/egg/tests/__init__.py
src/minitage/recipe/egg/tests/conservative.txt
src/minitage/recipe/egg/tests/custom.txt
src/minitage/recipe/egg/tests/distribute.txt
src/minitage/recipe/egg/tests/fromurl.txt
src/minitage/recipe/egg/tests/md5.txt
src/minitage/recipe/egg/tests/patch.txt
src/minitage/recipe/egg/tests/special_distribute.txt
src/minitage/recipe/egg/tests/test_doctest.py